yosemite/__init__.py
yosemite/__resources__/__init__.py
yosemite/data/__init__.py
yosemite/data/database.py
yosemite/data/document_reader.py
yosemite/llms/__init__.py
yosemite/llms/chatbot.py
yosemite/llms/chatui.py
yosemite/llms/instruct.py
yosemite/llms/llm.py
yosemite/llms/moe.py
yosemite/llms/rag.py
yosemite/nlp/__init__.py
yosemite/nlp/chunker.py
yosemite/nlp/nlp.py
yosemite/nlp/sentences.py
yosemite/tools/__init__.py
yosemite/tools/tools.py
yosemite-0.1.15.dist-info/METADATA
yosemite-0.1.15.dist-info/WHEEL
yosemite-0.1.15.dist-info/entry_points.txt
yosemite-0.1.15.dist-info/top_level.txt
yosemite-0.1.15.dist-info/RECORD
