Metadata-Version: 2.1
Name: yosemite
Version: 0.1.15
Summary: yosemite
Author: Hammad Saeed
Author-email: hammad@supportvectors.com
Classifier: Programming Language :: Python :: 3
Classifier: License :: OSI Approved :: MIT License
Classifier: Operating System :: OS Independent
Requires-Python: >3.8
Requires-Dist: monterey
Requires-Dist: fastapi
Requires-Dist: uvicorn
Requires-Dist: pydantic
Requires-Dist: customtkinter
Requires-Dist: elevenlabs
Requires-Dist: wcwidth
Requires-Dist: annoy
Requires-Dist: anthropic
Requires-Dist: ebooklib
Requires-Dist: instructor
Requires-Dist: mistralai
Requires-Dist: pandas
Requires-Dist: pathlib
Requires-Dist: pdfminer.six
Requires-Dist: PyPDF2
Requires-Dist: sentence-transformers
Requires-Dist: spacy
Requires-Dist: wheel
Requires-Dist: Whoosh
